testdefinitionsmkdocs/__init__.py
mkdocs_test_definitions_plugin-1.2.dist-info/METADATA
mkdocs_test_definitions_plugin-1.2.dist-info/WHEEL
mkdocs_test_definitions_plugin-1.2.dist-info/entry_points.txt
mkdocs_test_definitions_plugin-1.2.dist-info/top_level.txt
mkdocs_test_definitions_plugin-1.2.dist-info/RECORD
