Metadata-Version: 2.1
Name: mkdocs-test-definitions-plugin
Version: 1.2
Summary: An MkDocs plugin that converts LAVA test definitions to documentation
Home-page: https://github.com/linaro/test-definitions
Author: Milosz Wasilewski
Author-email: milosz.wasilewski@linaro.org
License: GPL
Keywords: mkdocs python markdown wiki
Platform: UNKNOWN
Classifier: Development Status :: 5 - Production/Stable
Classifier: Intended Audience :: Developers
Classifier: Intended Audience :: Information Technology
Classifier: License :: OSI Approved :: GNU General Public License v2 or later (GPLv2+)
Classifier: Programming Language :: Python
Classifier: Programming Language :: Python :: 3 :: Only
Classifier: Programming Language :: Python :: 3.5
Classifier: Programming Language :: Python :: 3.6
Classifier: Programming Language :: Python :: 3.7
Requires-Python: >=3.5
Requires-Dist: mkdocs (>=1.1)
Requires-Dist: tags-macros-plugin
